xero_python/__init__.py
xero_python-0.1.0.dist-info/AUTHORS.md
xero_python-0.1.0.dist-info/LICENSE
xero_python-0.1.0.dist-info/METADATA
xero_python-0.1.0.dist-info/WHEEL
xero_python-0.1.0.dist-info/top_level.txt
xero_python-0.1.0.dist-info/RECORD
