Metadata-Version: 2.1
Name: xero-python
Version: 0.1.0
Summary: Official Python sdk for Xero API generated by OpenAPI spec for oAuth2
Home-page: UNKNOWN
Author: Xero Developer API
Author-email: api@xero.com
License: MIT license
Keywords: xero python sdk API oAuth
Platform: UNKNOWN
Classifier: Development Status :: 2 - Pre-Alpha
Classifier: Intended Audience :: Developers
Classifier: License :: OSI Approved :: MIT License
Classifier: Natural Language :: English
Classifier: Programming Language :: Python :: 3
Classifier: Programming Language :: Python :: 3.5
Classifier: Programming Language :: Python :: 3.6
Classifier: Programming Language :: Python :: 3.7
Classifier: Programming Language :: Python :: 3.8
Requires-Python: >=3.5
